{
  "presets": {
    "default": {
      "name": "Default",
      "flipHorizontal": false,
      "flipVertical": false,
      "rotate": 0,
      "invert": false,
      "speed": 150,
      "sensitivity": 128,
      "soundEnabled": true,
      "soundVolume": 0.3
    },
    "mirror": {
      "name": "Mirror Mode",
      "flipHorizontal": true,
      "flipVertical": false,
      "rotate": 0,
      "invert": false,
      "speed": 100,
      "sensitivity": 128,
      "soundEnabled": true,
      "soundVolume": 0.3
    },
    "inverted": {
      "name": "Inverted Display",
      "flipHorizontal": false,
      "flipVertical": false,
      "rotate": 0,
      "invert": true,
      "speed": 150,
      "sensitivity": 100,
      "soundEnabled": true,
      "soundVolume": 0.3
    },
    "rotated_90": {
      "name": "Rotated 90°",
      "flipHorizontal": false,
      "flipVertical": false,
      "rotate": 90,
      "invert": false,
      "speed": 200,
      "sensitivity": 128,
      "soundEnabled": true,
      "soundVolume": 0.3
    },
    "rotated_180": {
      "name": "Rotated 180°",
      "flipHorizontal": false,
      "flipVertical": false,
      "rotate": 180,
      "invert": false,
      "speed": 150,
      "sensitivity": 128,
      "soundEnabled": true,
      "soundVolume": 0.3
    },
    "flipped_both": {
      "name": "Double Flip",
      "flipHorizontal": true,
      "flipVertical": true,
      "rotate": 0,
      "invert": false,
      "speed": 150,
      "sensitivity": 128,
      "soundEnabled": true,
      "soundVolume": 0.3
    },
    "high_contrast": {
      "name": "High Contrast",
      "flipHorizontal": false,
      "flipVertical": false,
      "rotate": 0,
      "invert": false,
      "speed": 100,
      "sensitivity": 200,
      "soundEnabled": true,
      "soundVolume": 0.3
    },
    "low_contrast": {
      "name": "Low Contrast",
      "flipHorizontal": false,
      "flipVertical": false,
      "rotate": 0,
      "invert": false,
      "speed": 150,
      "sensitivity": 50,
      "soundEnabled": true,
      "soundVolume": 0.3
    },
    "fast_flip": {
      "name": "Fast Flip",
      "flipHorizontal": false,
      "flipVertical": false,
      "rotate": 0,
      "invert": false,
      "speed": 50,
      "sensitivity": 128,
      "soundEnabled": true,
      "soundVolume": 0.5
    },
    "slow_mechanical": {
      "name": "Slow Mechanical",
      "flipHorizontal": false,
      "flipVertical": false,
      "rotate": 0,
      "invert": false,
      "speed": 400,
      "sensitivity": 128,
      "soundEnabled": true,
      "soundVolume": 0.8
    },
    "silent": {
      "name": "Silent Mode",
      "flipHorizontal": false,
      "flipVertical": false,
      "rotate": 0,
      "invert": false,
      "speed": 150,
      "sensitivity": 128,
      "soundEnabled": false,
      "soundVolume": 0.0
    }
  },
  "userPresets": {}
}
